dask_pyspy/__init__.py
dask_pyspy/prctl.py
dask_pyspy/pyspy.py
dask_pyspy-0.4.0.dist-info/LICENSE
dask_pyspy-0.4.0.dist-info/WHEEL
dask_pyspy-0.4.0.dist-info/METADATA
dask_pyspy-0.4.0.dist-info/RECORD
