Metadata-Version: 2.1
Name: dask-pyspy
Version: 0.4.0
Summary: Profile dask distributed clusters with py-spy
License: MIT
Author: Gabe Joseph
Author-email: gjoseph92@gmail.com
Requires-Python: >=3.8,<4.0
Classifier: License :: OSI Approved :: MIT License
Classifier: Programming Language :: Python :: 3
Classifier: Programming Language :: Python :: 3.8
Classifier: Programming Language :: Python :: 3.9
Classifier: Programming Language :: Python :: 3.10
Classifier: Programming Language :: Python :: 3.11
Requires-Dist: distributed (>=2.30.0)
Requires-Dist: py-spy (>=0.3.9,<0.4.0)
